git_repo_info/__init__.py
git_repo_info/git_repo_info.py
git_repo_info-0.4.0.dist-info/DESCRIPTION.rst
git_repo_info-0.4.0.dist-info/METADATA
git_repo_info-0.4.0.dist-info/RECORD
git_repo_info-0.4.0.dist-info/WHEEL
git_repo_info-0.4.0.dist-info/metadata.json
git_repo_info-0.4.0.dist-info/top_level.txt
